rpi_temperature_mqtt/__init__.py
rpi_temperature_mqtt/logger.py
rpi_temperature_mqtt-0.0.6.data/scripts/rpi-temperature-mqtt
rpi_temperature_mqtt-0.0.6.dist-info/LICENSE
rpi_temperature_mqtt-0.0.6.dist-info/METADATA
rpi_temperature_mqtt-0.0.6.dist-info/WHEEL
rpi_temperature_mqtt-0.0.6.dist-info/top_level.txt
rpi_temperature_mqtt-0.0.6.dist-info/RECORD
