Metadata-Version: 2.1
Name: rpi-temperature-mqtt
Version: 0.0.6
Summary: Send temperature from DS18B20 sensors to mqtt broker
Home-page: https://github.com/goodfield/rpi-temperature-mqtt.git
Author: David Uebelacker
Author-email: david@uebelacker.ch
License: The MIT License (MIT)
Requires-Dist: paho-mqtt
